setup.cfg
setup.py
api_transilien_manager/__init__.py
api_transilien_manager/command_line.py
api_transilien_manager/mod_01_extract_api.py
api_transilien_manager/mod_01_extract_schedule.py
api_transilien_manager/mod_02_query_schedule.py
api_transilien_manager/mod_03_match_collections.py
api_transilien_manager/settings.py
api_transilien_manager/task_01_d_move_col.py
api_transilien_manager/task_01_h_extract_api.py
api_transilien_manager/task_01_single_cycle_api.py
api_transilien_manager/task_01_w_extract_schedule.py
api_transilien_manager/task_02_d_sch_dep.py
api_transilien_manager/task_03_d_match.py
api_transilien_manager/utils_api_client.py
api_transilien_manager/utils_misc.py
api_transilien_manager/utils_mongo.py
api_transilien_manager/utils_rdb.py
api_transilien_manager/utils_secrets.py
api_transilien_manager.egg-info/PKG-INFO
api_transilien_manager.egg-info/SOURCES.txt
api_transilien_manager.egg-info/dependency_links.txt
api_transilien_manager.egg-info/top_level.txt
test/test_01_extract_api.py
test/test_01_extract_schedule.py
test/test_02_query_schedule.py
test/test_03_match_collections.py
test/test_utils_misc.py