Metadata-Version: 1.0
Name: api-transilien-manager
Version: 0.0.2
Summary: Task manager to exploit data from transilien's api
Home-page: https://github.com/leonardbinet/Transilien-Api
Author: Leonard Binet
Author-email: leonardbinet@gmail.com
License: MIT
Platform: UNKNOWN
